{
  "best-film": [
    {
      "name": "Spotlight",
      "awards": {
        "gg": "X",
        "bafta": "X",
        "oscar": "Y",
        "afi": "Y",
        "sag": "Y",
        "critics": "Y",
        "pga": "X",
        "lafca": "Y",
        "nbr": "Y",
        "gotham": "Y",
        "wga": "Y",
        "spirit": "Y"
      },
      "genre": "Drama",
      "posterPath": "/8DPGG400FgaFWaqcv11n8mRd2NG.jpg",
      "tmdbId": 314365
    },
    {
      "name": "The Martian",
      "awards": {
        "gg": "Y",
        "oscar": "X",
        "afi": "Y",
        "critics": "X",
        "pga": "X",
        "nbr": "Y",
        "wga": "X",
        "adg": "Y"
      },
      "genre": "Comedy",
      "posterPath": "/3ndAx3weG6KDkJIRMCi5vXX6Dyb.jpg",
      "tmdbId": 286217
    },
    {
      "name": "Mad Max: Fury Road",
      "awards": {
        "gg": "X",
        "oscar": "X",
        "afi": "Y",
        "critics": "X",
        "pga": "X",
        "lafca": "X",
        "nbr": "Y",
        "adg": "Y"
      },
      "genre": "Drama",
      "posterPath": "/hA2ple9q4qnwxp3hKVNhroipsir.jpg",
      "tmdbId": 76341
    },
    {
      "name": "The Big Short",
      "awards": {
        "gg": "X",
        "bafta": "X",
        "oscar": "X",
        "afi": "Y",
        "sag": "X",
        "critics": "X",
        "pga": "Y",
        "wga": "Y"
      },
      "genre": "Comedy",
      "posterPath": "/scVEaJEwP8zUix8vgmMoJJ9Nq0w.jpg",
      "tmdbId": 318846
    },
    {
      "name": "The Revenant",
      "awards": {
        "gg": "Y",
        "bafta": "Y",
        "oscar": "X",
        "critics": "X",
        "pga": "X",
        "adg": "Y"
      },
      "genre": "Drama",
      "posterPath": "/ji3ecJphATlVgWNY0B0RVXZizdf.jpg",
      "tmdbId": 281957
    },
    {
      "name": "Bridge of Spies",
      "awards": {
        "bafta": "X",
        "oscar": "X",
        "afi": "Y",
        "critics": "X",
        "pga": "X",
        "nbr": "Y",
        "wga": "X",
        "adg": "X"
      },
      "posterPath": "/fmOOjHAQzxr0c1sfcY4qkiSRBH6.jpg",
      "tmdbId": 296098
    },
    {
      "name": "Room",
      "awards": {
        "gg": "X",
        "oscar": "X",
        "afi": "Y",
        "critics": "X",
        "nbr": "Y"
      },
      "genre": "Drama",
      "posterPath": "/2hHDMeYyZjbGWn0BeNH1cTMxuM7.jpg",
      "tmdbId": 264644
    },
    {
      "name": "Straight Outta Compton",
      "awards": {
        "afi": "Y",
        "sag": "X",
        "pga": "X",
        "nbr": "Y",
        "wga": "X"
      },
      "posterPath": "/1CiLJx8Xtv3TbbFj6k7BboSmKgC.jpg",
      "tmdbId": 277216
    },
    {
      "name": "Inside Out",
      "awards": {
        "afi": "Y",
        "nbr": "Y"
      },
      "posterPath": "/2H1TmgdfNtsKlU9jKdeNyYL5y8T.jpg",
      "tmdbId": 150540
    },
    {
      "name": "Carol",
      "awards": {
        "gg": "X",
        "bafta": "X",
        "afi": "Y",
        "critics": "X",
        "gotham": "X",
        "wga": "X",
        "spirit": "X"
      },
      "genre": "Drama",
      "posterPath": "/cJeled7EyPdur6TnCA5GYg0UVna.jpg",
      "tmdbId": 258480
    },
    {
      "name": "Sicario",
      "awards": {
        "critics": "X",
        "pga": "X",
        "nbr": "Y",
        "wga": "X",
        "adg": "X"
      },
      "posterPath": "/lz8vNyXeidqqOdJW9ZjnDAMb5Vr.jpg",
      "tmdbId": 273481
    },
    {
      "name": "Star Wars: The Force Awakens",
      "awards": {
        "afi": "Y",
        "critics": "X",
        "adg": "X"
      },
      "posterPath": "/wqnLdwVXoBjKibFRR5U3y0aDUhs.jpg",
      "tmdbId": 140607
    },
    {
      "name": "Ti guardo",
      "awards": {
        "venice": "Y"
      },
      "posterPath": "/lxExFOPqTbm08e50T23eapbavV6.jpg",
      "tmdbId": 345269
    },
    {
      "name": "Creed",
      "awards": {
        "nbr": "Y"
      },
      "posterPath": "/1BfTsk5VWuw8FCocAhCyqnRbEzq.jpg",
      "tmdbId": 312221
    },
    {
      "name": "The Hateful Eight",
      "awards": {
        "nbr": "Y"
      },
      "posterPath": "/jIywvdPjia2t3eKYbjVTcwBQlG8.jpg",
      "tmdbId": 273248
    },
    {
      "name": "Brooklyn",
      "awards": {
        "oscar": "X",
        "critics": "X",
        "pga": "X"
      },
      "posterPath": "/eqVRQcGhl1CRRjjct78tRR2SPrk.jpg",
      "tmdbId": 291678
    },
    {
      "name": "Trumbo",
      "awards": {
        "sag": "X",
        "wga": "X",
        "adg": "X"
      },
      "posterPath": "/2RERIRnZkROSeHZAIf8PSxhzOqs.jpg",
      "tmdbId": 294016
    },
    {
      "name": "Joy",
      "awards": {
        "gg": "X",
        "adg": "X"
      },
      "genre": "Comedy",
      "posterPath": "/nZAs0HbW82TI1i4Xid83M941Pki.jpg",
      "tmdbId": 274479
    },
    {
      "name": "Trainwreck",
      "awards": {
        "gg": "X",
        "wga": "X"
      },
      "genre": "Comedy",
      "posterPath": "/wrY629UTCUAKLJ4CxQXz6DCE7pr.jpg",
      "tmdbId": 271718
    },
    {
      "name": "Beasts of No Nation",
      "awards": {
        "sag": "X",
        "spirit": "X"
      },
      "posterPath": "/1D4vcJmJc58WXarpRtwgd2do9Rg.jpg",
      "tmdbId": 283587
    },
    {
      "name": "Ex Machina",
      "awards": {
        "pga": "X",
        "adg": "X"
      },
      "posterPath": "/dmJW8IAKHKxFNiUnoDR7JfsK7Rp.jpg",
      "tmdbId": 264660
    },
    {
      "name": "Tangerine",
      "awards": {
        "gotham": "X",
        "spirit": "X"
      },
      "posterPath": "/EKLR5c61XQzBTeMokFrmS3kdt8.jpg",
      "tmdbId": 308084
    },
    {
      "name": "Spy",
      "awards": {
        "gg": "X"
      },
      "genre": "Comedy",
      "posterPath": "/vPBmfMHxQvRRNGYD5S5ko2KnX56.jpg",
      "tmdbId": 238713
    },
    {
      "name": "The Diary of a Teenage Girl",
      "awards": {
        "gotham": "X"
      },
      "posterPath": "/5YlUrdYKuscD7pwf3yy9duVLbui.jpg",
      "tmdbId": 250124
    },
    {
      "name": "Heaven Knows What",
      "awards": {
        "gotham": "X"
      },
      "posterPath": "/E1MMMNAd01p3nMkUIB6eFtB57J.jpg",
      "tmdbId": 285024
    },
    {
      "name": "Steve Jobs",
      "awards": {
        "wga": "X"
      },
      "screenplay_type": "adapted",
      "posterPath": "/ljiRO29Y9khEERRqMluptUYunJ9.jpg",
      "tmdbId": 321697
    },
    {
      "name": "Anomalisa",
      "awards": {
        "spirit": "X"
      },
      "posterPath": "/4DJ1zNr4Y6q7zQ27goEYla46VdO.jpg",
      "tmdbId": 291270
    },
    {
      "name": "Crimson Peak",
      "awards": {
        "adg": "X"
      },
      "posterPath": "/f9TOb5anVwZeSbYjU1qNxPk3KUk.jpg",
      "tmdbId": 201085
    },
    {
      "name": "The Danish Girl",
      "awards": {
        "adg": "X"
      },
      "posterPath": "/mXZZIacI5FC8thzSC0lgQBQ2uAX.jpg",
      "tmdbId": 306819
    },
    {
      "name": "Cinderella",
      "awards": {
        "adg": "X"
      },
      "posterPath": "/j91LJmcWo16CArFOoapsz84bwxb.jpg",
      "tmdbId": 150689
    },
    {
      "name": "Jurassic World",
      "awards": {
        "adg": "X"
      },
      "posterPath": "/1RICxzeoNCAO5NpcRMIgg1XT6fm.jpg",
      "tmdbId": 1234821
    },
    {
      "name": "Tomorrowland",
      "awards": {
        "adg": "X"
      },
      "posterPath": "/kziYpr5Nfw60P0My8aj1sgCEqed.jpg",
      "tmdbId": 158852
    },
    {
      "name": "Spectre",
      "awards": {
        "adg": "X"
      },
      "posterPath": "/zj8ongFhtWNsVlfjOGo8pSr7PQg.jpg",
      "tmdbId": 206647
    }
  ],
  "best-director": [
    {
      "name": "George Miller",
      "awards": {
        "gg": "X",
        "oscar": "X",
        "critics": "Y",
        "dga": "X",
        "lafca": "Y"
      },
      "film": "Mad Max: Fury Road",
      "profilePath": "/35NQ8HjFXQlGYDz9UkhT08lKl5C.jpg",
      "tmdbId": 20629
    },
    {
      "name": "Alejandro G. Iñárritu",
      "awards": {
        "gg": "Y",
        "oscar": "Y",
        "critics": "X"
      },
      "film": "The Revenant",
      "profilePath": "/Av0jewh8wltCl1CB8MfEIrvgfMZ.jpg",
      "tmdbId": 223
    },
    {
      "name": "Alejandro González Iñárritu",
      "film": "The Revenant",
      "awards": {
        "bafta": "Y",
        "dga": "Y"
      },
      "profilePath": "/Av0jewh8wltCl1CB8MfEIrvgfMZ.jpg",
      "tmdbId": 223
    },
    {
      "name": "Tom McCarthy",
      "awards": {
        "gg": "X",
        "oscar": "X",
        "critics": "X",
        "dga": "X",
        "spirit": "Y"
      },
      "film": "Spotlight"
    },
    {
      "name": "Ridley Scott",
      "awards": {
        "gg": "X",
        "bafta": "X",
        "critics": "X",
        "dga": "X",
        "nbr": "Y"
      },
      "film": "The Martian",
      "profilePath": "/zABJmN9opmqD4orWl3KSdCaSo7Q.jpg",
      "tmdbId": 578
    },
    {
      "name": "Pablo Trapero",
      "awards": {
        "venice": "Y"
      },
      "film": "Il clan",
      "profilePath": "/h8qZtRXhyheacl37J3MYx7aN05G.jpg",
      "tmdbId": 56210
    },
    {
      "name": "Todd Haynes",
      "awards": {
        "gg": "X",
        "bafta": "X",
        "critics": "X",
        "lafca": "X",
        "spirit": "X"
      },
      "film": "Carol",
      "profilePath": "/wBDazO2j49uoquoHTEDxcniyGGC.jpg",
      "tmdbId": 16863
    },
    {
      "name": "Adam McKay",
      "film": "The Big Short",
      "awards": {
        "bafta": "X",
        "oscar": "X",
        "dga": "X"
      }
    },
    {
      "name": "Steven Spielberg",
      "film": "Bridge of Spies",
      "awards": {
        "bafta": "X",
        "critics": "X"
      },
      "profilePath": "/tZxcg19YQ3e8fJ0pOs7hjlnmmr6.jpg",
      "tmdbId": 488
    },
    {
      "name": "Lenny Abrahamson",
      "film": "Room",
      "awards": {
        "oscar": "X"
      },
      "profilePath": "/tQYjfuxoZW9JrMqdiIdZMc9OEnR.jpg",
      "tmdbId": 83281
    },
    {
      "name": "Sean Baker",
      "awards": {
        "spirit": "X"
      },
      "film": "Tangerine",
      "profilePath": "/wKfNgfRvPhLHMrwuweSwLOmhRzT.jpg",
      "tmdbId": 118415
    },
    {
      "name": "Cary Joji Fukunaga",
      "awards": {
        "spirit": "X"
      },
      "film": "Beasts of No Nation",
      "profilePath": "/uVh6HtOwDxOxrjIbUMeRz5b0A7S.jpg",
      "tmdbId": 87257
    },
    {
      "name": "Charlie Kaufman  and  Duke Johnson",
      "awards": {
        "spirit": "X"
      },
      "film": "Anomalisa"
    },
    {
      "name": "David Robert Mitchell",
      "awards": {
        "spirit": "X"
      },
      "film": "It Follows",
      "profilePath": "/i0XKqclsHNO8JAD7yNuuUNOUXG3.jpg",
      "tmdbId": 558929
    }
  ],
  "best-actor": [
    {
      "name": "Leonardo DiCaprio",
      "awards": {
        "gg": "Y",
        "bafta": "Y",
        "oscar": "Y",
        "sag": "Y",
        "critics": "Y"
      },
      "film": "The Revenant",
      "role": "Leading",
      "profilePath": "/wo2hJpn04vbtmh0B9utCFdsQhxM.jpg",
      "tmdbId": 6193
    },
    {
      "name": "Mark Rylance",
      "awards": {
        "gg": "X",
        "bafta": "Y",
        "oscar": "Y",
        "sag": "X",
        "critics": "X",
        "lafca": "X"
      },
      "film": "Bridge of Spies",
      "role": "Leading",
      "profilePath": "/bztEZRyXrvW3Pg1fexNASXlZrq7.jpg",
      "tmdbId": 40900
    },
    {
      "name": "Matt Damon",
      "awards": {
        "gg": "Y",
        "bafta": "X",
        "oscar": "X",
        "critics": "X",
        "nbr": "Y"
      },
      "film": "The Martian",
      "role": "Leading",
      "profilePath": "/At3JgvaNeEN4Z4ESKlhhes85Xo3.jpg",
      "tmdbId": 1892
    },
    {
      "name": "Idris Elba",
      "awards": {
        "gg": "X",
        "bafta": "X",
        "sag": "Y",
        "spirit": "Y"
      },
      "film": "Beasts of No Nation",
      "role": "Leading",
      "profilePath": "/be1bVF7qGX91a6c5WeRPs5pKXln.jpg",
      "tmdbId": 17605
    },
    {
      "name": "Sylvester Stallone",
      "awards": {
        "gg": "Y",
        "oscar": "X",
        "critics": "Y"
      },
      "film": "Creed",
      "role": "Leading",
      "profilePath": "/gn3pDWthJqR0VDYGViGD3048og7.jpg",
      "tmdbId": 16483
    },
    {
      "name": "Michael Fassbender",
      "awards": {
        "gg": "X",
        "bafta": "X",
        "oscar": "X",
        "sag": "X",
        "critics": "X",
        "lafca": "Y"
      },
      "film": "Steve Jobs",
      "role": "Leading",
      "profilePath": "/xvbnUiB2ZBR3QIt595OzNy657Vw.jpg",
      "tmdbId": 17288
    },
    {
      "name": "Michael Shannon",
      "awards": {
        "gg": "X",
        "sag": "X",
        "critics": "X",
        "lafca": "Y",
        "gotham": "X",
        "spirit": "X"
      },
      "film": "99 Homes",
      "role": "Leading",
      "profilePath": "/6mMczfjM8CiS1WuBOgo5Xom1TcR.jpg",
      "tmdbId": 335
    },
    {
      "name": "Paul Dano",
      "awards": {
        "gg": "X",
        "critics": "X",
        "gotham": "Y",
        "spirit": "X"
      },
      "film": "Love & Mercy",
      "role": "Leading",
      "profilePath": "/zEJJsm0z07EPNl2Pi1h67xuCmcA.jpg",
      "tmdbId": 17142
    },
    {
      "name": "Fabrice Luchini",
      "awards": {
        "venice": "Y"
      },
      "film": "La corte",
      "profilePath": "/krR5EUfM13UJwsB07ffzPU7FXYR.jpg",
      "tmdbId": 28255
    },
    {
      "name": "Abraham Attah",
      "awards": {
        "spirit": "Y"
      },
      "film": "Beasts of No Nation",
      "profilePath": "/8r5GdE98NDuj8hMJktXtFWVtxxl.jpg",
      "tmdbId": 1421427
    },
    {
      "name": "Bryan Cranston",
      "awards": {
        "gg": "X",
        "bafta": "X",
        "oscar": "X",
        "sag": "X",
        "critics": "X"
      },
      "film": "Trumbo",
      "role": "Leading",
      "profilePath": "/npIIZJGSrcJIJ6yHdmbqO6Jzo5I.jpg",
      "tmdbId": 17419
    },
    {
      "name": "Eddie Redmayne",
      "awards": {
        "gg": "X",
        "bafta": "X",
        "oscar": "X",
        "sag": "X",
        "critics": "X"
      },
      "film": "The Danish Girl",
      "role": "Leading",
      "profilePath": "/fSvG7qzoBBnJUmgtIuMgrK3EQPN.jpg",
      "tmdbId": 37632
    },
    {
      "name": "Christian Bale",
      "awards": {
        "gg": "X",
        "bafta": "X",
        "oscar": "X",
        "sag": "X"
      },
      "film": "The Big Short",
      "role": "Leading",
      "profilePath": "/gbcLQi7lQVaIF3WXNjW9Fqi84xZ.jpg",
      "tmdbId": 3894
    },
    {
      "name": "Mark Ruffalo",
      "film": "Spotlight",
      "role": "Supporting",
      "awards": {
        "bafta": "X",
        "oscar": "X",
        "critics": "X"
      },
      "profilePath": "/5GilHMOt5PAQh6rlUKZzGmaKEI7.jpg",
      "tmdbId": 103
    },
    {
      "name": "Tom Hardy",
      "film": "The Revenant",
      "role": "Supporting",
      "awards": {
        "oscar": "X",
        "critics": "X"
      },
      "profilePath": "/d81K0RH8UX7tZj49tZaQhZ9ewH.jpg",
      "tmdbId": 2524
    },
    {
      "name": "Johnny Depp",
      "awards": {
        "sag": "X",
        "critics": "X"
      },
      "film": "Black Mass",
      "role": "Leading",
      "profilePath": "/drl9qDZoxPHhUbDamYcOQEhlHzW.jpg",
      "tmdbId": 85
    },
    {
      "name": "Christopher Abbott",
      "awards": {
        "gotham": "X",
        "spirit": "X"
      },
      "film": "James White",
      "profilePath": "/qWmlTycQb3yXaGhxPb6LCyaDjqh.jpg",
      "tmdbId": 984629
    },
    {
      "name": "Kevin Corrigan",
      "awards": {
        "gotham": "X",
        "spirit": "X"
      },
      "film": "Results",
      "profilePath": "/obSUGc68mQDvFONalMg25Xw5GZM.jpg",
      "tmdbId": 18472
    },
    {
      "name": "Will Smith",
      "awards": {
        "gg": "X"
      },
      "film": "Concussion",
      "role": "Leading",
      "profilePath": "/8TlKqbXYgHmmaEoPBJ7djJ8Rxxa.jpg",
      "tmdbId": 2888
    },
    {
      "name": "Steve Carell",
      "awards": {
        "gg": "X"
      },
      "film": "The Big Short",
      "role": "Leading",
      "profilePath": "/ULqKHMosznI7U2JyRZYMvSxUvq.jpg",
      "tmdbId": 4495
    },
    {
      "name": "Al Pacino",
      "awards": {
        "gg": "X"
      },
      "film": "Danny Collins",
      "role": "Leading",
      "profilePath": "/iqJ6g9fTKjpp1zWH9v72whXeGIK.jpg",
      "tmdbId": 1158
    },
    {
      "name": "Mark Ruffalo",
      "awards": {
        "gg": "X"
      },
      "film": "Infinitely Polar Bear",
      "role": "Leading",
      "profilePath": "/5GilHMOt5PAQh6rlUKZzGmaKEI7.jpg",
      "tmdbId": 103
    },
    {
      "name": "Benicio del Toro",
      "film": "Sicario",
      "role": "Supporting",
      "awards": {
        "bafta": "X"
      },
      "profilePath": "/cVh4UgCMu6aAkZ2BqymTLV86FzZ.jpg",
      "tmdbId": 1121
    },
    {
      "name": "Jacob Tremblay",
      "awards": {
        "sag": "X"
      },
      "film": "Room",
      "role": "Supporting",
      "profilePath": "/h8CXDp86Y36CUENF4SXJq5ZRTsf.jpg",
      "tmdbId": 1277188
    },
    {
      "name": "Géza Röhrig",
      "awards": {
        "lafca": "X"
      },
      "film": "Son of Saul",
      "profilePath": "/3XrYcL5wC1wQnmqJautgZK3XuiM.jpg",
      "tmdbId": 1454942
    },
    {
      "name": "Peter Sarsgaard",
      "awards": {
        "gotham": "X"
      },
      "film": "Experimenter",
      "profilePath": "/gYnEJjeHgZVBZh6aGzgfzm4jIHM.jpg",
      "tmdbId": 133
    },
    {
      "name": "Ben Mendelsohn",
      "awards": {
        "spirit": "X"
      },
      "film": "Mississippi Grind",
      "profilePath": "/pA9mu9D2IolVA0v2Yo0tJm6uUyI.jpg",
      "tmdbId": 77335
    },
    {
      "name": "Jason Segel",
      "awards": {
        "spirit": "X"
      },
      "film": "The End of the Tour",
      "profilePath": "/aG6tVNSbl1YEjN65G3luFYnWbUM.jpg",
      "tmdbId": 41088
    },
    {
      "name": "Koudous Seihon",
      "awards": {
        "spirit": "X"
      },
      "film": "Mediterranea",
      "profilePath": "/y7QkiYovyuZ0f4DOCVr44QTviu0.jpg",
      "tmdbId": 1456984
    },
    {
      "name": "Richard Jenkins",
      "awards": {
        "spirit": "X"
      },
      "film": "Bone Tomahawk",
      "profilePath": "/muT3RZG9hiKaKojD751RcQ5tGEy.jpg",
      "tmdbId": 28633
    }
  ],
  "best-actress": [
    {
      "name": "Brie Larson",
      "awards": {
        "gg": "Y",
        "bafta": "Y",
        "oscar": "Y",
        "sag": "Y",
        "critics": "Y",
        "nbr": "Y",
        "gotham": "X",
        "spirit": "Y"
      },
      "film": "Room",
      "role": "Leading",
      "profilePath": "/xSGvMwNNJcEQvVcjiIUTyxyMfkZ.jpg",
      "tmdbId": 60073
    },
    {
      "name": "Alicia Vikander",
      "awards": {
        "gg": "X",
        "bafta": "X",
        "oscar": "Y",
        "sag": "Y",
        "critics": "Y"
      },
      "film": "The Danish Girl",
      "role": "Leading",
      "profilePath": "/9pmHTbXeRxUF51jJKthmHI49u9z.jpg",
      "tmdbId": 227454
    },
    {
      "name": "Kate Winslet",
      "awards": {
        "gg": "Y",
        "bafta": "Y",
        "oscar": "X",
        "sag": "X",
        "critics": "X"
      },
      "film": "Steve Jobs",
      "role": "Leading",
      "profilePath": "/9xDnfZrWhM67wJlQJEsOOjQzDUQ.jpg",
      "tmdbId": 204
    },
    {
      "name": "Jennifer Lawrence",
      "awards": {
        "gg": "Y",
        "oscar": "X",
        "critics": "X"
      },
      "film": "Joy",
      "role": "Leading",
      "profilePath": "/mDKMsjOMytyBiy7MHNZTa7gp7wj.jpg",
      "tmdbId": 72129
    },
    {
      "name": "Alicia Vikander",
      "awards": {
        "gg": "X",
        "bafta": "X",
        "lafca": "Y"
      },
      "film": "Ex Machina",
      "role": "Leading",
      "profilePath": "/9pmHTbXeRxUF51jJKthmHI49u9z.jpg",
      "tmdbId": 227454
    },
    {
      "name": "Charlotte Rampling",
      "film": "45 Years",
      "role": "Leading",
      "awards": {
        "oscar": "X",
        "critics": "X",
        "lafca": "Y"
      },
      "profilePath": "/Htvl9mN6mlf2a18RAFzNXF3RiG.jpg",
      "tmdbId": 44079
    },
    {
      "name": "Bel Powley",
      "awards": {
        "gotham": "Y",
        "spirit": "X"
      },
      "film": "The Diary of a Teenage Girl",
      "profilePath": "/xlzi5lol9UBvYK9Dw8AEQObSbrm.jpg",
      "tmdbId": 1201716
    },
    {
      "name": "Valeria Golino",
      "awards": {
        "venice": "Y"
      },
      "film": "Per amor vostro",
      "profilePath": "/bLw0lNPEhICtbTLtnTswamefN7C.jpg",
      "tmdbId": 3124
    },
    {
      "name": "Mya Taylor",
      "awards": {
        "spirit": "Y"
      },
      "film": "Tangerine",
      "profilePath": "/tKkNUKQJJVUcPSsK8E8jLpVRe57.jpg",
      "tmdbId": 1393916
    },
    {
      "name": "Cate Blanchett",
      "awards": {
        "gg": "X",
        "bafta": "X",
        "oscar": "X",
        "sag": "X",
        "critics": "X",
        "gotham": "X",
        "spirit": "X"
      },
      "film": "Carol",
      "role": "Leading",
      "profilePath": "/vq4vuAVhYngfzVNn8SbnG0JEy15.jpg",
      "tmdbId": 112
    },
    {
      "name": "Rooney Mara",
      "awards": {
        "gg": "X",
        "bafta": "X",
        "oscar": "X",
        "sag": "X",
        "critics": "X",
        "spirit": "X"
      },
      "film": "Carol",
      "role": "Leading",
      "profilePath": "/zT6UyHFHEQ9RcKykplWCycKBnoS.jpg",
      "tmdbId": 108916
    },
    {
      "name": "Saoirse Ronan",
      "awards": {
        "gg": "X",
        "bafta": "X",
        "oscar": "X",
        "sag": "X",
        "critics": "X",
        "lafca": "X"
      },
      "film": "Brooklyn",
      "role": "Leading",
      "profilePath": "/w88uhQ5f8CXw9pQx5HtDrDpzQ4x.jpg",
      "tmdbId": 36592
    },
    {
      "name": "Jennifer Jason Leigh",
      "awards": {
        "gg": "X",
        "bafta": "X",
        "oscar": "X",
        "critics": "X"
      },
      "film": "The Hateful Eight",
      "role": "Leading",
      "profilePath": "/yYD255SwZkFc1wGgBMVRZ2i7Ina.jpg",
      "tmdbId": 10431
    },
    {
      "name": "Helen Mirren",
      "awards": {
        "gg": "X",
        "sag": "X",
        "critics": "X"
      },
      "film": "Trumbo",
      "role": "Leading",
      "profilePath": "/1reKRrsdsHXJaRVHVyOEg4oPTcZ.jpg",
      "tmdbId": 15735
    },
    {
      "name": "Rachel McAdams",
      "film": "Spotlight",
      "role": "Supporting",
      "awards": {
        "oscar": "X",
        "sag": "X",
        "critics": "X"
      },
      "profilePath": "/2zyOjda95OfAAsJvuwTV0UaznPZ.jpg",
      "tmdbId": 53714
    },
    {
      "name": "Maggie Smith",
      "awards": {
        "gg": "X",
        "bafta": "X"
      },
      "film": "The Lady in the Van",
      "role": "Leading",
      "profilePath": "/i7vcF4KzJTgH6kO0TqURuEEfoU3.jpg",
      "tmdbId": 10978
    },
    {
      "name": "Lily Tomlin",
      "awards": {
        "gg": "X",
        "gotham": "X"
      },
      "film": "Grandma",
      "role": "Leading",
      "profilePath": "/eoFMSqRykiaXMGCiz7Kxehfqy1W.jpg",
      "tmdbId": 10437
    },
    {
      "name": "Melissa McCarthy",
      "awards": {
        "gg": "X"
      },
      "film": "Spy",
      "role": "Leading",
      "profilePath": "/yl0qva0O4u92fvtItakdvKmKrW9.jpg",
      "tmdbId": 55536
    },
    {
      "name": "Amy Schumer",
      "awards": {
        "gg": "X"
      },
      "film": "Trainwreck",
      "role": "Leading",
      "profilePath": "/saXAIob0JOf8B4Z9v2pgzEHV8wb.jpg",
      "tmdbId": 440414
    },
    {
      "name": "Jane Fonda",
      "awards": {
        "gg": "X"
      },
      "film": "Youth",
      "role": "Leading",
      "profilePath": "/5Yb3nmRWXXZAxNhfhEuOMdfyVNN.jpg",
      "tmdbId": 6352
    },
    {
      "name": "Julie Walters",
      "film": "Brooklyn",
      "role": "Supporting",
      "awards": {
        "bafta": "X"
      },
      "profilePath": "/bCTkV2OUgzbJdQEoCk3GesE4DXq.jpg",
      "tmdbId": 477
    },
    {
      "name": "Helen Mirren",
      "awards": {
        "sag": "X"
      },
      "film": "Woman in Gold",
      "role": "Leading",
      "profilePath": "/1reKRrsdsHXJaRVHVyOEg4oPTcZ.jpg",
      "tmdbId": 15735
    },
    {
      "name": "Sarah Silverman",
      "awards": {
        "sag": "X"
      },
      "film": "I Smile Back",
      "role": "Leading",
      "profilePath": "/g5G711XyVokJm2RoItpkaHa8mkQ.jpg",
      "tmdbId": 7404
    },
    {
      "name": "Charlize Theron",
      "film": "Mad Max: Fury Road",
      "role": "Leading",
      "awards": {
        "critics": "X"
      },
      "profilePath": "/ie1KbeYFG5E0GVr1QP7tDNuXvga.jpg",
      "tmdbId": 6885
    },
    {
      "name": "Kristen Stewart",
      "awards": {
        "lafca": "X"
      },
      "film": "Clouds of Sils Maria",
      "profilePath": "/ryhCjTGqS6G6OprbR0qUEH355lA.jpg",
      "tmdbId": 37917
    },
    {
      "name": "Blythe Danner",
      "awards": {
        "gotham": "X"
      },
      "film": "I'll See You in My Dreams",
      "profilePath": "/xIN3nX76b4qN8B32wdoqx053N68.jpg",
      "tmdbId": 10401
    },
    {
      "name": "Kristen Wiig",
      "awards": {
        "gotham": "X"
      },
      "film": "Welcome to Me",
      "profilePath": "/oddvykQHx71hEZlvKinCzB3Vcfh.jpg",
      "tmdbId": 41091
    },
    {
      "name": "Kitana Kiki Rodriguez",
      "awards": {
        "spirit": "X"
      },
      "film": "Tangerine",
      "profilePath": "/iR8bJguB5TGPXJCHIT42ICIWTBs.jpg",
      "tmdbId": 1393915
    },
    {
      "name": "Robin Bartlett",
      "awards": {
        "spirit": "X"
      },
      "film": "H.",
      "profilePath": "/94OpCjYBbxIoCtJpFWAlFQornKO.jpg",
      "tmdbId": 11902
    },
    {
      "name": "Marin Ireland",
      "awards": {
        "spirit": "X"
      },
      "film": "Glass Chin",
      "profilePath": "/jAIOQNraHjvIAdqk81QDV5Phupp.jpg",
      "tmdbId": 164094
    },
    {
      "name": "Jennifer Jason Leigh",
      "awards": {
        "spirit": "X"
      },
      "film": "Anomalisa",
      "profilePath": "/yYD255SwZkFc1wGgBMVRZ2i7Ina.jpg",
      "tmdbId": 10431
    },
    {
      "name": "Cynthia Nixon",
      "awards": {
        "spirit": "X"
      },
      "film": "James White",
      "profilePath": "/a366FCtQYmT80vQnPMFZ4hsTwuU.jpg",
      "tmdbId": 38024
    }
  ]
}